{
  "env_type": "circles",
  "difficulty": "hard",
  "resolution": 0.05,
  "noise_level": 0.01,
  "workspace_bounds": [
    -1,
    11,
    -1,
    11
  ],
  "clustering_eps": 0.3,
  "min_samples": 5,
  "obstacle_type": "auto",
  "num_points": 13296,
  "num_obstacles": 16,
  "seed": 7819,
  "environment_details": {
    "environment_type": "circle_only",
    "config": {
      "num_obstacles": 16,
      "obstacle_size_range": [
        0.2,
        1.0
      ],
      "density_level": "dense",
      "complexity_level": "complex",
      "spatial_distribution": "distributed",
      "workspace_utilization": 0.8,
      "min_distance_factor": 0.8
    },
    "num_obstacles": 16,
    "obstacles": [
      {
        "id": 0,
        "position": [
          6.3700270652771,
          4.695531368255615
        ],
        "radius": 1.4179683923721313,
        "type": "circle"
      },
      {
        "id": 1,
        "position": [
          6.098569393157959,
          1.836363434791565
        ],
        "radius": 0.12661872804164886,
        "type": "circle"
      },
      {
        "id": 2,
        "position": [
          1.6500378847122192,
          6.5533599853515625
        ],
        "radius": 1.334557294845581,
        "type": "circle"
      },
      {
        "id": 3,
        "position": [
          8.369394302368164,
          1.5395362377166748
        ],
        "radius": 0.696394681930542,
        "type": "circle"
      },
      {
        "id": 4,
        "position": [
          4.968620300292969,
          6.921401500701904
        ],
        "radius": 0.35724711418151855,
        "type": "circle"
      },
      {
        "id": 5,
        "position": [
          2.082249641418457,
          7.132452011108398
        ],
        "radius": 1.6582101583480835,
        "type": "circle"
      },
      {
        "id": 6,
        "position": [
          2.3407533168792725,
          0.9709088206291199
        ],
        "radius": 0.6096928715705872,
        "type": "circle"
      },
      {
        "id": 7,
        "position": [
          3.456221103668213,
          1.7965008020401
        ],
        "radius": 0.3570598363876343,
        "type": "circle"
      },
      {
        "id": 8,
        "position": [
          9.255228996276855,
          0.9476276636123657
        ],
        "radius": 1.5744966268539429,
        "type": "circle"
      },
      {
        "id": 9,
        "position": [
          8.931740760803223,
          2.0438389778137207
        ],
        "radius": 0.44648364186286926,
        "type": "circle"
      },
      {
        "id": 10,
        "position": [
          2.592794179916382,
          5.723876476287842
        ],
        "radius": 0.35317549109458923,
        "type": "circle"
      },
      {
        "id": 11,
        "position": [
          6.633951187133789,
          2.5553736686706543
        ],
        "radius": 1.018053412437439,
        "type": "circle"
      },
      {
        "id": 12,
        "position": [
          3.6473581790924072,
          0.7471345067024231
        ],
        "radius": 0.8740682005882263,
        "type": "circle"
      },
      {
        "id": 13,
        "position": [
          3.0981619358062744,
          5.023736953735352
        ],
        "radius": 0.1718480885028839,
        "type": "circle"
      },
      {
        "id": 14,
        "position": [
          3.8119897842407227,
          7.397291660308838
        ],
        "radius": 0.5978338122367859,
        "type": "circle"
      },
      {
        "id": 15,
        "position": [
          1.5059655904769897,
          5.055080413818359
        ],
        "radius": 0.7763652205467224,
        "type": "circle"
      }
    ],
    "workspace_bounds": [
      0,
      10,
      0,
      8
    ],
    "robot_base_position": [
      0,
      0
    ],
    "generation_timestamp": null
  },
  "generation_timestamp": "2025-07-14T16:45:30.857301"
}