{
  "env_type": "circles",
  "difficulty": "hard",
  "resolution": 0.05,
  "noise_level": 0.01,
  "workspace_bounds": [
    -1,
    11,
    -1,
    11
  ],
  "clustering_eps": 0.3,
  "min_samples": 5,
  "obstacle_type": "auto",
  "num_points": 6922,
  "num_obstacles": 9,
  "seed": 1782,
  "environment_details": {
    "environment_type": "circle_only",
    "config": {
      "num_obstacles": 9,
      "obstacle_size_range": [
        0.2,
        1.0
      ],
      "density_level": "dense",
      "complexity_level": "complex",
      "spatial_distribution": "distributed",
      "workspace_utilization": 0.8,
      "min_distance_factor": 0.8
    },
    "num_obstacles": 9,
    "obstacles": [
      {
        "id": 0,
        "position": [
          1.778731107711792,
          6.225988388061523
        ],
        "radius": 0.1519460678100586,
        "type": "circle"
      },
      {
        "id": 1,
        "position": [
          1.633766770362854,
          2.982882499694824
        ],
        "radius": 1.3815962076187134,
        "type": "circle"
      },
      {
        "id": 2,
        "position": [
          5.288414478302002,
          2.5080864429473877
        ],
        "radius": 0.22793276607990265,
        "type": "circle"
      },
      {
        "id": 3,
        "position": [
          3.124577045440674,
          3.5113418102264404
        ],
        "radius": 0.3255545198917389,
        "type": "circle"
      },
      {
        "id": 4,
        "position": [
          4.1219964027404785,
          6.73874568939209
        ],
        "radius": 0.9277678728103638,
        "type": "circle"
      },
      {
        "id": 5,
        "position": [
          6.843153476715088,
          7.205160617828369
        ],
        "radius": 1.2970722913742065,
        "type": "circle"
      },
      {
        "id": 6,
        "position": [
          8.734077453613281,
          4.69990873336792
        ],
        "radius": 0.44658559560775757,
        "type": "circle"
      },
      {
        "id": 7,
        "position": [
          3.744291067123413,
          5.038401126861572
        ],
        "radius": 0.33514106273651123,
        "type": "circle"
      },
      {
        "id": 8,
        "position": [
          2.922329902648926,
          1.8696972131729126
        ],
        "radius": 0.8696607947349548,
        "type": "circle"
      }
    ],
    "workspace_bounds": [
      0,
      10,
      0,
      8
    ],
    "robot_base_position": [
      0,
      0
    ],
    "generation_timestamp": null
  },
  "generation_timestamp": "2025-07-14T16:23:22.448603"
}