{
  "env_type": "circles",
  "difficulty": "random",
  "resolution": 0.05,
  "noise_level": 0.01,
  "workspace_bounds": [
    -1,
    11,
    -1,
    11
  ],
  "clustering_eps": 0.3,
  "min_samples": 5,
  "obstacle_type": "auto",
  "num_points": 1301,
  "num_obstacles": 3,
  "seed": 3566,
  "environment_details": {
    "environment_type": "circle_only",
    "config": {
      "num_obstacles": 3,
      "obstacle_size_range": [
        0.35,
        0.65
      ],
      "density_level": "dense",
      "complexity_level": "simple",
      "spatial_distribution": "line",
      "workspace_utilization": 0.36887329957354237,
      "min_distance_factor": 0.6270001759388957
    },
    "num_obstacles": 3,
    "obstacles": [
      {
        "id": 0,
        "position": [
          7.196450233459473,
          3.3705296516418457
        ],
        "radius": 0.5488366484642029,
        "type": "circle"
      },
      {
        "id": 1,
        "position": [
          5.018415451049805,
          0.7858359217643738
        ],
        "radius": 0.7890989780426025,
        "type": "circle"
      },
      {
        "id": 2,
        "position": [
          5.467985153198242,
          5.905557155609131
        ],
        "radius": 0.3340374231338501,
        "type": "circle"
      }
    ],
    "workspace_bounds": [
      0,
      10,
      0,
      8
    ],
    "robot_base_position": [
      0,
      0
    ],
    "generation_timestamp": null
  },
  "generation_timestamp": "2025-07-14T16:29:56.189702"
}