{
  "env_type": "circles",
  "difficulty": "medium",
  "resolution": 0.05,
  "noise_level": 0.01,
  "workspace_bounds": [
    -1,
    11,
    -1,
    11
  ],
  "clustering_eps": 0.3,
  "min_samples": 5,
  "obstacle_type": "auto",
  "num_points": 942,
  "num_obstacles": 5,
  "seed": 6985,
  "environment_details": {
    "environment_type": "circle_only",
    "config": {
      "num_obstacles": 5,
      "obstacle_size_range": [
        0.2,
        0.6
      ],
      "density_level": "medium",
      "complexity_level": "medium",
      "spatial_distribution": "clusters",
      "workspace_utilization": 0.6,
      "min_distance_factor": 1.2
    },
    "num_obstacles": 5,
    "obstacles": [
      {
        "id": 0,
        "position": [
          3.758937120437622,
          4.282098293304443
        ],
        "radius": 0.11517266929149628,
        "type": "circle"
      },
      {
        "id": 1,
        "position": [
          3.130061149597168,
          3.9880988597869873
        ],
        "radius": 0.25951558351516724,
        "type": "circle"
      },
      {
        "id": 2,
        "position": [
          5.102443218231201,
          6.337851047515869
        ],
        "radius": 0.5600667595863342,
        "type": "circle"
      },
      {
        "id": 3,
        "position": [
          7.228541374206543,
          2.512263536453247
        ],
        "radius": 0.31849196553230286,
        "type": "circle"
      },
      {
        "id": 4,
        "position": [
          3.333423614501953,
          6.168031215667725
        ],
        "radius": 0.5021196007728577,
        "type": "circle"
      }
    ],
    "workspace_bounds": [
      0,
      10,
      0,
      8
    ],
    "robot_base_position": [
      0,
      0
    ],
    "generation_timestamp": null
  },
  "generation_timestamp": "2025-07-14T16:42:23.509848"
}