{
  "env_type": "circles",
  "difficulty": "hard",
  "resolution": 0.05,
  "noise_level": 0.01,
  "workspace_bounds": [
    -1,
    11,
    -1,
    11
  ],
  "clustering_eps": 0.3,
  "min_samples": 5,
  "obstacle_type": "auto",
  "num_points": 3618,
  "num_obstacles": 9,
  "seed": 5748,
  "environment_details": {
    "environment_type": "circle_only",
    "config": {
      "num_obstacles": 9,
      "obstacle_size_range": [
        0.2,
        1.0
      ],
      "density_level": "dense",
      "complexity_level": "complex",
      "spatial_distribution": "distributed",
      "workspace_utilization": 0.8,
      "min_distance_factor": 0.8
    },
    "num_obstacles": 9,
    "obstacles": [
      {
        "id": 0,
        "position": [
          7.622267246246338,
          2.0185511112213135
        ],
        "radius": 0.5451503396034241,
        "type": "circle"
      },
      {
        "id": 1,
        "position": [
          3.1522254943847656,
          3.546795606613159
        ],
        "radius": 0.4378301203250885,
        "type": "circle"
      },
      {
        "id": 2,
        "position": [
          3.5292391777038574,
          4.368986129760742
        ],
        "radius": 1.214847445487976,
        "type": "circle"
      },
      {
        "id": 3,
        "position": [
          3.906327247619629,
          2.304168462753296
        ],
        "radius": 0.7267730236053467,
        "type": "circle"
      },
      {
        "id": 4,
        "position": [
          6.937404632568359,
          5.9774580001831055
        ],
        "radius": 0.3671480715274811,
        "type": "circle"
      },
      {
        "id": 5,
        "position": [
          6.64542293548584,
          5.365950107574463
        ],
        "radius": 0.4573637843132019,
        "type": "circle"
      },
      {
        "id": 6,
        "position": [
          6.03764533996582,
          1.681007981300354
        ],
        "radius": 0.3113213777542114,
        "type": "circle"
      },
      {
        "id": 7,
        "position": [
          5.976524353027344,
          1.0831202268600464
        ],
        "radius": 0.3064042329788208,
        "type": "circle"
      },
      {
        "id": 8,
        "position": [
          4.060251235961914,
          4.581818580627441
        ],
        "radius": 0.7667745351791382,
        "type": "circle"
      }
    ],
    "workspace_bounds": [
      0,
      10,
      0,
      8
    ],
    "robot_base_position": [
      0,
      0
    ],
    "generation_timestamp": null
  },
  "generation_timestamp": "2025-07-14T16:37:54.788600"
}