{
  "env_type": "circles",
  "difficulty": "expert",
  "resolution": 0.05,
  "noise_level": 0.01,
  "workspace_bounds": [
    -1,
    11,
    -1,
    11
  ],
  "clustering_eps": 0.3,
  "min_samples": 5,
  "obstacle_type": "auto",
  "num_points": 10143,
  "num_obstacles": 20,
  "seed": 9373,
  "environment_details": {
    "environment_type": "circle_only",
    "config": {
      "num_obstacles": 20,
      "obstacle_size_range": [
        0.1,
        1.2
      ],
      "density_level": "dense",
      "complexity_level": "complex",
      "spatial_distribution": "line",
      "workspace_utilization": 0.9,
      "min_distance_factor": 0.5
    },
    "num_obstacles": 20,
    "obstacles": [
      {
        "id": 0,
        "position": [
          6.0657477378845215,
          3.8262035846710205
        ],
        "radius": 0.06243966519832611,
        "type": "circle"
      },
      {
        "id": 1,
        "position": [
          4.694611549377441,
          4.561954498291016
        ],
        "radius": 0.6053907871246338,
        "type": "circle"
      },
      {
        "id": 2,
        "position": [
          8.295528411865234,
          5.18699312210083
        ],
        "radius": 1.3665560483932495,
        "type": "circle"
      },
      {
        "id": 3,
        "position": [
          5.209383487701416,
          2.6738898754119873
        ],
        "radius": 0.48599618673324585,
        "type": "circle"
      },
      {
        "id": 4,
        "position": [
          1.5364291667938232,
          6.818480968475342
        ],
        "radius": 0.7206441164016724,
        "type": "circle"
      },
      {
        "id": 5,
        "position": [
          7.528011798858643,
          2.7814278602600098
        ],
        "radius": 0.15911893546581268,
        "type": "circle"
      },
      {
        "id": 6,
        "position": [
          3.890742063522339,
          1.1937161684036255
        ],
        "radius": 0.09979785978794098,
        "type": "circle"
      },
      {
        "id": 7,
        "position": [
          7.844053745269775,
          3.806330442428589
        ],
        "radius": 0.45055440068244934,
        "type": "circle"
      },
      {
        "id": 8,
        "position": [
          8.648965835571289,
          6.262828826904297
        ],
        "radius": 0.8346197605133057,
        "type": "circle"
      },
      {
        "id": 9,
        "position": [
          7.645078659057617,
          0.616665780544281
        ],
        "radius": 1.5888057947158813,
        "type": "circle"
      },
      {
        "id": 10,
        "position": [
          5.208191394805908,
          3.914900779724121
        ],
        "radius": 0.6574166417121887,
        "type": "circle"
      },
      {
        "id": 11,
        "position": [
          6.170019626617432,
          3.303663969039917
        ],
        "radius": 0.6620742678642273,
        "type": "circle"
      },
      {
        "id": 12,
        "position": [
          3.17578125,
          1.993209958076477
        ],
        "radius": 0.3836395740509033,
        "type": "circle"
      },
      {
        "id": 13,
        "position": [
          1.9886656999588013,
          7.3163838386535645
        ],
        "radius": 0.17329707741737366,
        "type": "circle"
      },
      {
        "id": 14,
        "position": [
          7.878688335418701,
          5.302081108093262
        ],
        "radius": 0.49076855182647705,
        "type": "circle"
      },
      {
        "id": 15,
        "position": [
          8.953660011291504,
          6.534708499908447
        ],
        "radius": 0.9265762567520142,
        "type": "circle"
      },
      {
        "id": 16,
        "position": [
          3.8822102546691895,
          4.197033405303955
        ],
        "radius": 0.1173328086733818,
        "type": "circle"
      },
      {
        "id": 17,
        "position": [
          2.9498414993286133,
          0.9887590408325195
        ],
        "radius": 0.8539246916770935,
        "type": "circle"
      },
      {
        "id": 18,
        "position": [
          8.870753288269043,
          7.061436176300049
        ],
        "radius": 0.2158505618572235,
        "type": "circle"
      },
      {
        "id": 19,
        "position": [
          4.8723649978637695,
          0.5758590698242188
        ],
        "radius": 0.42985332012176514,
        "type": "circle"
      }
    ],
    "workspace_bounds": [
      0,
      10,
      0,
      8
    ],
    "robot_base_position": [
      0,
      0
    ],
    "generation_timestamp": null
  },
  "generation_timestamp": "2025-07-14T16:51:14.498186"
}