{
  "env_type": "circles",
  "difficulty": "expert",
  "resolution": 0.05,
  "noise_level": 0.01,
  "workspace_bounds": [
    -1,
    11,
    -1,
    11
  ],
  "clustering_eps": 0.3,
  "min_samples": 5,
  "obstacle_type": "auto",
  "num_points": 7022,
  "num_obstacles": 13,
  "seed": 8964,
  "environment_details": {
    "environment_type": "circle_only",
    "config": {
      "num_obstacles": 13,
      "obstacle_size_range": [
        0.1,
        1.2
      ],
      "density_level": "dense",
      "complexity_level": "complex",
      "spatial_distribution": "line",
      "workspace_utilization": 0.9,
      "min_distance_factor": 0.5
    },
    "num_obstacles": 13,
    "obstacles": [
      {
        "id": 0,
        "position": [
          5.295679092407227,
          5.775052070617676
        ],
        "radius": 0.6614012718200684,
        "type": "circle"
      },
      {
        "id": 1,
        "position": [
          3.7077929973602295,
          4.180067539215088
        ],
        "radius": 0.3829681873321533,
        "type": "circle"
      },
      {
        "id": 2,
        "position": [
          6.472916126251221,
          5.409356117248535
        ],
        "radius": 0.9740661382675171,
        "type": "circle"
      },
      {
        "id": 3,
        "position": [
          3.4815030097961426,
          4.548666477203369
        ],
        "radius": 0.8025233745574951,
        "type": "circle"
      },
      {
        "id": 4,
        "position": [
          4.724265098571777,
          4.210855007171631
        ],
        "radius": 1.079221248626709,
        "type": "circle"
      },
      {
        "id": 5,
        "position": [
          7.298685073852539,
          4.092006206512451
        ],
        "radius": 0.7279632687568665,
        "type": "circle"
      },
      {
        "id": 6,
        "position": [
          1.1908196210861206,
          6.032787322998047
        ],
        "radius": 1.0146607160568237,
        "type": "circle"
      },
      {
        "id": 7,
        "position": [
          2.174311876296997,
          3.9717652797698975
        ],
        "radius": 0.6898971796035767,
        "type": "circle"
      },
      {
        "id": 8,
        "position": [
          8.572392463684082,
          4.896083354949951
        ],
        "radius": 0.2566332519054413,
        "type": "circle"
      },
      {
        "id": 9,
        "position": [
          3.2587971687316895,
          5.001285076141357
        ],
        "radius": 0.19675429165363312,
        "type": "circle"
      },
      {
        "id": 10,
        "position": [
          4.396923542022705,
          4.7056355476379395
        ],
        "radius": 0.27329036593437195,
        "type": "circle"
      },
      {
        "id": 11,
        "position": [
          2.7184386253356934,
          1.8508814573287964
        ],
        "radius": 0.7242393493652344,
        "type": "circle"
      },
      {
        "id": 12,
        "position": [
          3.2149429321289062,
          4.053003787994385
        ],
        "radius": 0.5249191522598267,
        "type": "circle"
      }
    ],
    "workspace_bounds": [
      0,
      10,
      0,
      8
    ],
    "robot_base_position": [
      0,
      0
    ],
    "generation_timestamp": null
  },
  "generation_timestamp": "2025-07-14T16:49:47.743353"
}