{
  "env_type": "circles",
  "difficulty": "easy",
  "resolution": 0.05,
  "noise_level": 0.01,
  "workspace_bounds": [
    -1,
    11,
    -1,
    11
  ],
  "clustering_eps": 0.3,
  "min_samples": 5,
  "obstacle_type": "auto",
  "num_points": 340,
  "num_obstacles": 3,
  "seed": 4363,
  "environment_details": {
    "environment_type": "circle_only",
    "config": {
      "num_obstacles": 3,
      "obstacle_size_range": [
        0.25,
        0.45
      ],
      "density_level": "sparse",
      "complexity_level": "simple",
      "spatial_distribution": "center",
      "workspace_utilization": 0.4,
      "min_distance_factor": 1.8
    },
    "num_obstacles": 3,
    "obstacles": [
      {
        "id": 0,
        "position": [
          5.5409064292907715,
          4.676551818847656
        ],
        "radius": 0.2239605188369751,
        "type": "circle"
      },
      {
        "id": 1,
        "position": [
          5.867175102233887,
          3.9549455642700195
        ],
        "radius": 0.2463192194700241,
        "type": "circle"
      },
      {
        "id": 2,
        "position": [
          4.318191051483154,
          4.803707599639893
        ],
        "radius": 0.400005966424942,
        "type": "circle"
      }
    ],
    "workspace_bounds": [
      0,
      10,
      0,
      8
    ],
    "robot_base_position": [
      0,
      0
    ],
    "generation_timestamp": null
  },
  "generation_timestamp": "2025-07-14T16:32:48.449751"
}