{
  "env_type": "circles",
  "difficulty": "medium",
  "resolution": 0.05,
  "noise_level": 0.01,
  "workspace_bounds": [
    -1,
    11,
    -1,
    11
  ],
  "clustering_eps": 0.3,
  "min_samples": 5,
  "obstacle_type": "auto",
  "num_points": 2507,
  "num_obstacles": 7,
  "seed": 5229,
  "environment_details": {
    "environment_type": "circle_only",
    "config": {
      "num_obstacles": 7,
      "obstacle_size_range": [
        0.3,
        0.7
      ],
      "density_level": "medium",
      "complexity_level": "medium",
      "spatial_distribution": "distributed",
      "workspace_utilization": 0.6,
      "min_distance_factor": 1.2
    },
    "num_obstacles": 7,
    "obstacles": [
      {
        "id": 0,
        "position": [
          5.393026351928711,
          5.584978103637695
        ],
        "radius": 0.738793134689331,
        "type": "circle"
      },
      {
        "id": 1,
        "position": [
          1.2783015966415405,
          7.454307556152344
        ],
        "radius": 0.40524035692214966,
        "type": "circle"
      },
      {
        "id": 2,
        "position": [
          9.153641700744629,
          2.737083911895752
        ],
        "radius": 0.3943606913089752,
        "type": "circle"
      },
      {
        "id": 3,
        "position": [
          1.2439497709274292,
          4.356308937072754
        ],
        "radius": 0.7258362770080566,
        "type": "circle"
      },
      {
        "id": 4,
        "position": [
          3.336984872817993,
          5.385699272155762
        ],
        "radius": 0.4615038335323334,
        "type": "circle"
      },
      {
        "id": 5,
        "position": [
          2.9150118827819824,
          7.18927526473999
        ],
        "radius": 0.5001441240310669,
        "type": "circle"
      },
      {
        "id": 6,
        "position": [
          6.61641263961792,
          4.369996070861816
        ],
        "radius": 0.3719230890274048,
        "type": "circle"
      }
    ],
    "workspace_bounds": [
      0,
      10,
      0,
      8
    ],
    "robot_base_position": [
      0,
      0
    ],
    "generation_timestamp": null
  },
  "generation_timestamp": "2025-07-14T16:35:55.213427"
}