{
  "env_type": "circles",
  "difficulty": "medium",
  "resolution": 0.05,
  "noise_level": 0.01,
  "workspace_bounds": [
    -1,
    11,
    -1,
    11
  ],
  "clustering_eps": 0.3,
  "min_samples": 5,
  "obstacle_type": "auto",
  "num_points": 1732,
  "num_obstacles": 7,
  "seed": 6292,
  "environment_details": {
    "environment_type": "circle_only",
    "config": {
      "num_obstacles": 7,
      "obstacle_size_range": [
        0.2,
        0.6
      ],
      "density_level": "medium",
      "complexity_level": "medium",
      "spatial_distribution": "clusters",
      "workspace_utilization": 0.6,
      "min_distance_factor": 1.2
    },
    "num_obstacles": 7,
    "obstacles": [
      {
        "id": 0,
        "position": [
          2.414555788040161,
          1.6778799295425415
        ],
        "radius": 0.6944996118545532,
        "type": "circle"
      },
      {
        "id": 1,
        "position": [
          3.2460954189300537,
          1.4771299362182617
        ],
        "radius": 0.4691545367240906,
        "type": "circle"
      },
      {
        "id": 2,
        "position": [
          2.8484551906585693,
          1.9175161123275757
        ],
        "radius": 0.4785996973514557,
        "type": "circle"
      },
      {
        "id": 3,
        "position": [
          3.673645257949829,
          2.4386849403381348
        ],
        "radius": 0.3667726516723633,
        "type": "circle"
      },
      {
        "id": 4,
        "position": [
          4.713407039642334,
          1.8913204669952393
        ],
        "radius": 0.6324386596679688,
        "type": "circle"
      },
      {
        "id": 5,
        "position": [
          4.261186122894287,
          2.5796797275543213
        ],
        "radius": 0.16694581508636475,
        "type": "circle"
      },
      {
        "id": 6,
        "position": [
          3.923496961593628,
          1.649356722831726
        ],
        "radius": 0.41572117805480957,
        "type": "circle"
      }
    ],
    "workspace_bounds": [
      0,
      10,
      0,
      8
    ],
    "robot_base_position": [
      0,
      0
    ],
    "generation_timestamp": null
  },
  "generation_timestamp": "2025-07-14T16:39:56.672969"
}