{
  "env_type": "circles",
  "difficulty": "random",
  "resolution": 0.05,
  "noise_level": 0.01,
  "workspace_bounds": [
    -1,
    11,
    -1,
    11
  ],
  "clustering_eps": 0.3,
  "min_samples": 5,
  "obstacle_type": "auto",
  "num_points": 4323,
  "num_obstacles": 8,
  "seed": 5165,
  "environment_details": {
    "environment_type": "circle_only",
    "config": {
      "num_obstacles": 8,
      "obstacle_size_range": [
        0.5,
        0.8
      ],
      "density_level": "sparse",
      "complexity_level": "medium",
      "spatial_distribution": "clusters",
      "workspace_utilization": 0.5519360198277071,
      "min_distance_factor": 1.8944391670497536
    },
    "num_obstacles": 8,
    "obstacles": [
      {
        "id": 0,
        "position": [
          5.8393449783325195,
          3.9283082485198975
        ],
        "radius": 0.42864200472831726,
        "type": "circle"
      },
      {
        "id": 1,
        "position": [
          7.877719879150391,
          5.86521053314209
        ],
        "radius": 0.4553934931755066,
        "type": "circle"
      },
      {
        "id": 2,
        "position": [
          8.842926025390625,
          6.758889675140381
        ],
        "radius": 0.6583409309387207,
        "type": "circle"
      },
      {
        "id": 3,
        "position": [
          4.06225061416626,
          6.756462574005127
        ],
        "radius": 0.574748694896698,
        "type": "circle"
      },
      {
        "id": 4,
        "position": [
          9.417712211608887,
          1.3900129795074463
        ],
        "radius": 0.9667524695396423,
        "type": "circle"
      },
      {
        "id": 5,
        "position": [
          2.5690865516662598,
          0.9428203701972961
        ],
        "radius": 0.8230047821998596,
        "type": "circle"
      },
      {
        "id": 6,
        "position": [
          6.465094089508057,
          0.5749894976615906
        ],
        "radius": 0.5710359215736389,
        "type": "circle"
      },
      {
        "id": 7,
        "position": [
          4.472497463226318,
          3.2469053268432617
        ],
        "radius": 0.5906204581260681,
        "type": "circle"
      }
    ],
    "workspace_bounds": [
      0,
      10,
      0,
      8
    ],
    "robot_base_position": [
      0,
      0
    ],
    "generation_timestamp": null
  },
  "generation_timestamp": "2025-07-14T16:35:41.208033"
}