{
  "env_type": "circles",
  "difficulty": "medium",
  "resolution": 0.05,
  "noise_level": 0.01,
  "workspace_bounds": [
    -1,
    11,
    -1,
    11
  ],
  "clustering_eps": 0.3,
  "min_samples": 5,
  "obstacle_type": "auto",
  "num_points": 2592,
  "num_obstacles": 8,
  "seed": 7817,
  "environment_details": {
    "environment_type": "circle_only",
    "config": {
      "num_obstacles": 8,
      "obstacle_size_range": [
        0.3,
        0.7
      ],
      "density_level": "medium",
      "complexity_level": "medium",
      "spatial_distribution": "clusters",
      "workspace_utilization": 0.6,
      "min_distance_factor": 1.2
    },
    "num_obstacles": 8,
    "obstacles": [
      {
        "id": 0,
        "position": [
          7.826306343078613,
          1.2630013227462769
        ],
        "radius": 0.7169189453125,
        "type": "circle"
      },
      {
        "id": 1,
        "position": [
          8.076809883117676,
          2.2411484718322754
        ],
        "radius": 0.32566946744918823,
        "type": "circle"
      },
      {
        "id": 2,
        "position": [
          7.079639911651611,
          1.9243284463882446
        ],
        "radius": 0.5246034860610962,
        "type": "circle"
      },
      {
        "id": 3,
        "position": [
          7.082186698913574,
          2.785783290863037
        ],
        "radius": 0.3113086223602295,
        "type": "circle"
      },
      {
        "id": 4,
        "position": [
          3.6228060722351074,
          3.327657699584961
        ],
        "radius": 0.5779514908790588,
        "type": "circle"
      },
      {
        "id": 5,
        "position": [
          2.721776247024536,
          3.2578649520874023
        ],
        "radius": 0.7918410301208496,
        "type": "circle"
      },
      {
        "id": 6,
        "position": [
          3.566319704055786,
          4.166014194488525
        ],
        "radius": 0.4172446131706238,
        "type": "circle"
      },
      {
        "id": 7,
        "position": [
          4.270391464233398,
          3.7038867473602295
        ],
        "radius": 0.3676017224788666,
        "type": "circle"
      }
    ],
    "workspace_bounds": [
      0,
      10,
      0,
      8
    ],
    "robot_base_position": [
      0,
      0
    ],
    "generation_timestamp": null
  },
  "generation_timestamp": "2025-07-14T16:45:29.998188"
}