{
  "env_type": "circles",
  "difficulty": "hard",
  "resolution": 0.05,
  "noise_level": 0.01,
  "workspace_bounds": [
    -1,
    11,
    -1,
    11
  ],
  "clustering_eps": 0.3,
  "min_samples": 5,
  "obstacle_type": "auto",
  "num_points": 4268,
  "num_obstacles": 12,
  "seed": 855,
  "environment_details": {
    "environment_type": "circle_only",
    "config": {
      "num_obstacles": 12,
      "obstacle_size_range": [
        0.2,
        1.0
      ],
      "density_level": "dense",
      "complexity_level": "complex",
      "spatial_distribution": "distributed",
      "workspace_utilization": 0.8,
      "min_distance_factor": 0.8
    },
    "num_obstacles": 12,
    "obstacles": [
      {
        "id": 0,
        "position": [
          4.83404541015625,
          3.0137619972229004
        ],
        "radius": 0.9631760120391846,
        "type": "circle"
      },
      {
        "id": 1,
        "position": [
          7.33723783493042,
          6.885408878326416
        ],
        "radius": 0.13526800274848938,
        "type": "circle"
      },
      {
        "id": 2,
        "position": [
          6.316506862640381,
          7.12221622467041
        ],
        "radius": 0.5339646339416504,
        "type": "circle"
      },
      {
        "id": 3,
        "position": [
          7.760085105895996,
          2.2387073040008545
        ],
        "radius": 0.8383762240409851,
        "type": "circle"
      },
      {
        "id": 4,
        "position": [
          1.8115233182907104,
          0.5751956105232239
        ],
        "radius": 0.5600919127464294,
        "type": "circle"
      },
      {
        "id": 5,
        "position": [
          5.049009799957275,
          0.6501879692077637
        ],
        "radius": 0.6975712776184082,
        "type": "circle"
      },
      {
        "id": 6,
        "position": [
          2.2682502269744873,
          6.117437839508057
        ],
        "radius": 0.3261978328227997,
        "type": "circle"
      },
      {
        "id": 7,
        "position": [
          6.991917610168457,
          5.682201862335205
        ],
        "radius": 0.16523432731628418,
        "type": "circle"
      },
      {
        "id": 8,
        "position": [
          2.1629583835601807,
          2.598473072052002
        ],
        "radius": 0.2294190526008606,
        "type": "circle"
      },
      {
        "id": 9,
        "position": [
          8.849989891052246,
          5.067367076873779
        ],
        "radius": 0.42532333731651306,
        "type": "circle"
      },
      {
        "id": 10,
        "position": [
          7.356476306915283,
          2.6355981826782227
        ],
        "radius": 0.2363019436597824,
        "type": "circle"
      },
      {
        "id": 11,
        "position": [
          5.055484294891357,
          5.0182600021362305
        ],
        "radius": 0.5497245192527771,
        "type": "circle"
      }
    ],
    "workspace_bounds": [
      0,
      10,
      0,
      8
    ],
    "robot_base_position": [
      0,
      0
    ],
    "generation_timestamp": null
  },
  "generation_timestamp": "2025-07-14T16:19:57.326793"
}